mypygui/__init__.py
mypygui/__main__.py
mypygui/browser_window/__init__.py
mypygui/core/__init__.py
mypygui/core/exceptions.py
mypygui/core/asynchronous/__init__.py
mypygui/core/asynchronous/async_tools.py
mypygui/core/asynchronous/decoraters.py
mypygui/core/fs/__init__.py
mypygui/core/fs/reading.py
mypygui/core/fs/uri.py
mypygui/core/services/__init__.py
mypygui/core/services/service_provider.py
mypygui/core/services/events/__init__.py
mypygui/core/services/events/event.py
mypygui/core/services/events/event_emitter.py
mypygui/core/services/events/event_handler.py
mypygui/core/services/layout_managing/__init__.py
mypygui/core/services/layout_managing/layout_handler.py
mypygui/core/services/rendering/__init__.py
mypygui/core/services/rendering/composite.py
mypygui/core/services/rendering/context.py
mypygui/core/services/rendering/window_provider.py
mypygui/core/services/resource_handling/__init__.py
mypygui/core/services/resource_handling/resource_handler.py
mypygui/core/services/worker/__init__.py
mypygui/core/services/worker/worker.py
mypygui/logging/__init__.py
mypygui/logging/console.py
mypygui/page/__init__.py
mypygui/page/clipboard.py
mypygui/page/page_globals.py
mypygui/page/page_loader.py
mypygui/page/page_loader_helper.py
mypygui/page/py_component.py
mypygui/page/css/__init__.py
mypygui/page/css/literals.py
mypygui/page/css/types.py
mypygui/page/objects/__init__.py
mypygui/page/objects/image_container.py
mypygui/page/objects/cssom/__init__.py
mypygui/page/objects/cssom/default_styles.py
mypygui/page/objects/cssom/style_sheet.py
mypygui/page/objects/dom/__init__.py
mypygui/page/objects/dom/location.py
mypygui/page/objects/dom/dom_node/__init__.py
mypygui/page/objects/dom/dom_node/dom_manipulation_helper.py
mypygui/page/objects/dom/dom_node/node.py
mypygui/page/objects/dom/dom_node/root.py
mypygui/page/objects/dom/dom_node/state_maintainers.py
mypygui/page/objects/dom/dom_node/style_container.py
mypygui/page/objects/render_tree/__init__.py
mypygui-0.0.17.dist-info/LICENSE
mypygui-0.0.17.dist-info/METADATA
mypygui-0.0.17.dist-info/WHEEL
mypygui-0.0.17.dist-info/top_level.txt
mypygui-0.0.17.dist-info/RECORD
