Metadata-Version: 2.1
Name: mypygui
Version: 0.0.17
Summary: Render basic html in python
Home-page: UNKNOWN
Author: Dragon-KK
License: LICENSE
Keywords: html,tkinter
Platform: UNKNOWN
Classifier: Programming Language :: Python :: 3
Classifier: License :: OSI Approved :: MIT License
Classifier: Operating System :: OS Independent
Requires-Python: >=3.10
License-File: LICENSE
Requires-Dist: pillow (>=9.1.0)
Requires-Dist: tinycss2 (>=1.1.1)
Requires-Dist: webcolors (>=1.12)
Requires-Dist: colorama (>=0.4.4)
Requires-Dist: requests (>=2.28.1)
